safeaipackage/__init__.py
safeaipackage/safeai.py
safeaipackage-0.6.0.dist-info/LICENSE
safeaipackage-0.6.0.dist-info/METADATA
safeaipackage-0.6.0.dist-info/WHEEL
safeaipackage-0.6.0.dist-info/top_level.txt
safeaipackage-0.6.0.dist-info/RECORD
